<?xml version="1.0" encoding="UTF-8"?>
<con:soapui-project id="2251e513-b3f5-4bcf-a976-5f4963f79e2b" activeEnvironment="Default" name="REST Project 1" soapui-version="5.7.2" abortOnError="false" runType="SEQUENTIAL" resourceRoot="" xmlns:con="http://eviware.com/soapui/config"><con:settings/><con:interface xsi:type="con:RestService" id="39e5d08b-2e58-4165-8c7a-446518724aa5" wadlVersion="http://wadl.dev.java.net/2009/02" name="http://localhost:8080" type="rest" xmlns:xsi="http://www.w3.org/2001/XMLSchema-instance"><con:settings/><con:definitionCache type="TEXT" rootPart=""/><con:endpoints><con:endpoint>http://localhost:8080</con:endpoint></con:endpoints><con:resource name="" path="/produto" id="3459d8cb-17fd-4402-a8fc-903c725f8950"><con:settings/><con:parameters><con:parameter><con:name>nome</con:name><con:style>TEMPLATE</con:style></con:parameter></con:parameters><con:resource name="sobremesa" path="sobremesa" id="14ede492-1a0a-4141-835a-a0b8c1b22e71"><con:settings/><con:parameters/><con:method name="lista" id="a606880e-6d5b-42c5-aa5c-bb92c54fb501" method="GET"><con:settings/><con:parameters/><con:representation type="RESPONSE"><con:mediaType>application/json</con:mediaType><con:status>200</con:status><con:params/><con:element>Response</con:element></con:representation><con:request name="Todas Sobremesas" id="14bd82dc-7bca-47e6-92f1-96c2a015b3a2" mediaType="application/json"><con:settings><con:setting id="com.eviware.soapui.impl.wsdl.WsdlRequest@request-headers">&lt;xml-fragment/></con:setting></con:settings><con:encoding>UTF-8</con:encoding><con:endpoint>http://localhost:8080</con:endpoint><con:request/><con:originalUri>http://localhost/produto/sobremesa</con:originalUri><con:credentials><con:authType>No Authorization</con:authType></con:credentials><con:jmsConfig JMSDeliveryMode="PERSISTENT"/><con:jmsPropertyConfig/><con:parameters/><con:parameterOrder/></con:request></con:method><con:method name="inclui" id="9d2de76e-a5af-4a72-839b-a769ac7d8c95" method="POST"><con:settings/><con:parameters/><con:representation type="REQUEST"><con:mediaType>application/json</con:mediaType><con:params/></con:representation><con:representation type="RESPONSE"><con:mediaType>application/json</con:mediaType><con:status>200</con:status><con:params/><con:element xmlns:sob="http://localhost/produto/sobremesa">sob:Response</con:element></con:representation><con:representation type="FAULT"><con:mediaType>application/json</con:mediaType><con:status>422 400</con:status><con:params/><con:element xmlns:sob="http://localhost/produto/sobremesa">sob:Fault</con:element></con:representation><con:request name="Nova Sobremesa" id="dae3d47b-e115-41ac-9e1a-452dd0ef01cd" mediaType="application/json" postQueryString="false"><con:settings><con:setting id="com.eviware.soapui.impl.wsdl.WsdlRequest@request-headers">&lt;xml-fragment/></con:setting></con:settings><con:encoding>UTF-8</con:encoding><con:endpoint>http://localhost:8080</con:endpoint><con:request>{
	"nome": "sobremesa", 
	"doce": true, 
	"informacao": "sobremesa", 
	"quantidade": 1, 
	"valor": 10
}</con:request><con:originalUri>http://localhost/produto/sobremesa</con:originalUri><con:credentials><con:authType>No Authorization</con:authType></con:credentials><con:jmsConfig JMSDeliveryMode="PERSISTENT"/><con:jmsPropertyConfig/><con:parameters><entry key="nome" value="sobremesa" xmlns="http://eviware.com/soapui/config"/></con:parameters><con:parameterOrder><con:entry>nome</con:entry></con:parameterOrder></con:request><con:request name="Erro nome do campo" id="dae3d47b-e115-41ac-9e1a-452dd0ef01cd" mediaType="application/json" postQueryString="false"><con:settings><con:setting id="com.eviware.soapui.impl.wsdl.WsdlRequest@request-headers">&lt;xml-fragment/></con:setting></con:settings><con:encoding>UTF-8</con:encoding><con:endpoint>http://localhost:8080</con:endpoint><con:request>{
	"nome1": "sobremesa", 
	"doce": true, 
	"informacao": "sobremesa", 
	"quantidade": 1, 
	"valor": 10
}</con:request><con:originalUri>http://localhost/produto/sobremesa</con:originalUri><con:credentials><con:authType>No Authorization</con:authType></con:credentials><con:jmsConfig JMSDeliveryMode="PERSISTENT"/><con:jmsPropertyConfig/><con:parameters><entry key="nome" value="sobremesa" xmlns="http://eviware.com/soapui/config"/></con:parameters><con:parameterOrder><con:entry>nome</con:entry></con:parameterOrder></con:request><con:request name="Erro validação" id="dae3d47b-e115-41ac-9e1a-452dd0ef01cd" mediaType="application/json" postQueryString="false"><con:settings><con:setting id="com.eviware.soapui.impl.wsdl.WsdlRequest@request-headers">&lt;xml-fragment/></con:setting></con:settings><con:encoding>UTF-8</con:encoding><con:endpoint>http://localhost:8080</con:endpoint><con:request>{
	"nome": " ", 
	"doce": true, 
	"informacao": "sobremesa", 
	"quantidade": -1, 
	"valor": 10
}</con:request><con:originalUri>http://localhost/produto/sobremesa</con:originalUri><con:credentials><con:authType>No Authorization</con:authType></con:credentials><con:jmsConfig JMSDeliveryMode="PERSISTENT"/><con:jmsPropertyConfig/><con:parameters><entry key="nome" value="sobremesa" xmlns="http://eviware.com/soapui/config"/></con:parameters><con:parameterOrder><con:entry>nome</con:entry></con:parameterOrder></con:request></con:method><con:method name="altera" id="9d136f7c-0a73-4463-9935-11e312419135" method="PUT"><con:settings/><con:parameters/><con:representation type="FAULT"><con:mediaType>application/problem+json</con:mediaType><con:status>405 400</con:status><con:params/><con:element xmlns:sob="http://localhost/produto/sobremesa">sob:Fault</con:element></con:representation><con:representation type="REQUEST"><con:mediaType>application/json</con:mediaType><con:params/></con:representation><con:representation type="RESPONSE"><con:mediaType>application/json</con:mediaType><con:status>200</con:status><con:params/><con:element xmlns:sob="http://localhost/produto/sobremesa">sob:Response</con:element></con:representation><con:representation type="RESPONSE"><con:mediaType xsi:nil="true"/><con:status>0</con:status><con:params/><con:element>data</con:element></con:representation><con:representation type="FAULT"><con:mediaType>application/json</con:mediaType><con:status>400</con:status><con:params/><con:element xmlns:sob="http://localhost/produto/sobremesa">sob:Fault</con:element></con:representation><con:request name="Altera Sobremesa" id="f6795040-4a08-4d82-9a05-38c0a41b7f51" mediaType="application/json" postQueryString="false"><con:description>Altera o valor</con:description><con:settings><con:setting id="com.eviware.soapui.impl.wsdl.WsdlRequest@request-headers">&lt;xml-fragment/></con:setting></con:settings><con:encoding>UTF-8</con:encoding><con:endpoint>http://localhost:8080</con:endpoint><con:request>   {
      "codigo": 4,
      "nome": "Brigadeiro Branco com Uva",
      "doce": true,
      "informacao": "Uma variação do brigadeiro tradicional que é feita com uvas Itália.",
      "quantidade": 0.1,
      "valor": 3.5
   }</con:request><con:originalUri>http://localhost/produto/sobremesa</con:originalUri><con:credentials><con:authType>No Authorization</con:authType></con:credentials><con:jmsConfig JMSDeliveryMode="PERSISTENT"/><con:jmsPropertyConfig/><con:parameters/></con:request><con:request name="Altera Sobremesa Erro Validação" id="f6795040-4a08-4d82-9a05-38c0a41b7f51" mediaType="application/json" postQueryString="false"><con:description>Altera o valor</con:description><con:settings><con:setting id="com.eviware.soapui.impl.wsdl.WsdlRequest@request-headers">&lt;xml-fragment/></con:setting></con:settings><con:encoding>UTF-8</con:encoding><con:endpoint>http://localhost:8080</con:endpoint><con:request>   {
      "codigo": 4,
      "nome": "Brigadeiro Branco com Uva",
      "doce": true,
      "informacao": "Uma variação do brigadeiro tradicional que é feita com uvas Itália.",
      "quantidade": -0.1,
      "valor": 3.5
   }</con:request><con:originalUri>http://localhost/produto/sobremesa</con:originalUri><con:credentials><con:authType>No Authorization</con:authType></con:credentials><con:jmsConfig JMSDeliveryMode="PERSISTENT"/><con:jmsPropertyConfig/><con:parameters/></con:request></con:method></con:resource><con:resource name="11" path="11" id="b77aa531-3d83-4e31-8332-2ac07fd50160"><con:settings/><con:parameters/><con:method name="consulta" id="f6f8f135-86c5-4e9c-bc73-1213060ef236" method="GET"><con:settings/><con:parameters/><con:representation type="RESPONSE"><con:mediaType>application/json</con:mediaType><con:status>200</con:status><con:params/><con:element xmlns:ns="http://localhost/produto/11">ns:Response</con:element></con:representation><con:request name="Consulta Produto Codigo 11" id="9748d82d-fcbc-4128-a160-1351581cfa9b" mediaType="application/json"><con:settings><con:setting id="com.eviware.soapui.impl.wsdl.WsdlRequest@request-headers">&lt;xml-fragment/></con:setting></con:settings><con:encoding>UTF-8</con:encoding><con:endpoint>http://localhost:8080</con:endpoint><con:request/><con:originalUri>http://localhost/produto/11</con:originalUri><con:credentials><con:authType>No Authorization</con:authType></con:credentials><con:jmsConfig JMSDeliveryMode="PERSISTENT"/><con:jmsPropertyConfig/><con:parameters/></con:request></con:method></con:resource><con:resource name="40" path="40" id="26a523d1-44be-4b5d-ba98-fdf7c7de081f"><con:settings/><con:parameters/><con:method name="apaga" id="50ec8a9e-7ea5-4174-8092-3f3f4fcd4794" method="DELETE"><con:settings/><con:parameters/><con:representation type="REQUEST"><con:mediaType>application/json</con:mediaType><con:params/></con:representation><con:representation type="FAULT"><con:mediaType>application/problem+json</con:mediaType><con:status>405</con:status><con:params/><con:element xmlns:ns="http://localhost/produto/7">ns:Fault</con:element></con:representation><con:representation type="FAULT"><con:mediaType>application/json</con:mediaType><con:status>500</con:status><con:params/><con:element xmlns:ns="http://localhost/produto/7">ns:Fault</con:element></con:representation><con:representation type="RESPONSE"><con:mediaType>application/json</con:mediaType><con:status>200</con:status><con:params/><con:element xmlns:ns="http://localhost/produto/7">ns:Response</con:element></con:representation><con:request name="Apaga Produto" id="5badf775-fbf4-43b2-91bd-89b37041fe5c" mediaType="application/json" postQueryString="false"><con:settings><con:setting id="com.eviware.soapui.impl.wsdl.WsdlRequest@request-headers">&lt;xml-fragment/></con:setting></con:settings><con:encoding>UTF-8</con:encoding><con:endpoint>http://localhost:8080</con:endpoint><con:request/><con:originalUri>http://localhost/produto/7</con:originalUri><con:credentials><con:authType>No Authorization</con:authType></con:credentials><con:jmsConfig JMSDeliveryMode="PERSISTENT"/><con:jmsPropertyConfig/><con:parameters/></con:request></con:method></con:resource><con:resource name="doce_tradicional" path="busca/doce_tradicional" id="999541ef-d5f0-44ba-b095-4ae9d0909ee5"><con:settings/><con:parameters/><con:method name="busca" id="87153159-a3ea-40b7-ac74-7a5a213fa2e4" method="GET"><con:settings/><con:parameters/><con:representation type="RESPONSE"><con:mediaType>application/json</con:mediaType><con:status>200</con:status><con:params/><con:element>Response</con:element></con:representation><con:request name="Busca produto por texto" id="cfe0177e-b8fc-4c1f-8e1d-8a3768b9cbcd" mediaType="application/json"><con:settings><con:setting id="com.eviware.soapui.impl.wsdl.WsdlRequest@request-headers">&lt;xml-fragment/></con:setting></con:settings><con:encoding>UTF-8</con:encoding><con:endpoint>http://localhost:8080</con:endpoint><con:request/><con:originalUri>http://localhost/produto/busca/doce_tradicional</con:originalUri><con:credentials><con:authType>No Authorization</con:authType></con:credentials><con:jmsConfig JMSDeliveryMode="PERSISTENT"/><con:jmsPropertyConfig/><con:parameters/></con:request></con:method></con:resource><con:resource name="6" path="6" id="47d699b7-bf3e-4e94-bc1f-7a1c4fdddfdd"><con:settings/><con:parameters/><con:method name="Apaga" id="0ca17861-b33c-4466-a69b-8b0aeadb20e8" method="DELETE"><con:settings/><con:parameters/><con:representation type="FAULT"><con:mediaType>application/json</con:mediaType><con:status>400 409</con:status><con:params/><con:element xmlns:ns="http://localhost/produto/6">ns:Fault</con:element></con:representation><con:representation type="REQUEST"><con:mediaType>application/json</con:mediaType><con:params/></con:representation><con:representation type="RESPONSE"><con:mediaType xsi:nil="true"/><con:status>0</con:status><con:params/><con:element>data</con:element></con:representation><con:representation type="RESPONSE"><con:mediaType xsi:nil="true"/><con:status>0</con:status><con:params/><con:element>data</con:element></con:representation><con:representation type="RESPONSE"><con:mediaType xsi:nil="true"/><con:status>0</con:status><con:params/><con:element>data</con:element></con:representation><con:request name="Erro produto sendo usado" id="788fad2d-9bc3-4920-ae98-2309a5b61895" mediaType="application/json" postQueryString="false"><con:settings><con:setting id="com.eviware.soapui.impl.wsdl.WsdlRequest@request-headers">&lt;xml-fragment/></con:setting></con:settings><con:encoding>UTF-8</con:encoding><con:endpoint>http://localhost:8080</con:endpoint><con:request/><con:originalUri>http://localhost/produto/6</con:originalUri><con:credentials><con:authType>No Authorization</con:authType></con:credentials><con:jmsConfig JMSDeliveryMode="PERSISTENT"/><con:jmsPropertyConfig/><con:parameters/></con:request></con:method></con:resource><con:resource name="bebida" path="bebida" id="6cafd9a0-9c07-4430-9f64-e3ae418cb8de"><con:settings/><con:parameters/><con:method name="lista" id="de2dfae9-59b2-4676-ba82-337f37347d87" method="GET"><con:settings/><con:parameters/><con:representation type="RESPONSE"><con:mediaType>application/json</con:mediaType><con:status>200</con:status><con:params/><con:element>Response</con:element></con:representation><con:request name="Todas Bebidas" id="1c8673f2-d3bd-4a57-854c-11fe254fa6e8" mediaType="application/json" postQueryString="false"><con:settings><con:setting id="com.eviware.soapui.impl.wsdl.WsdlRequest@request-headers">&lt;xml-fragment/></con:setting></con:settings><con:encoding>UTF-8</con:encoding><con:endpoint>http://localhost:8080</con:endpoint><con:request/><con:originalUri>http://localhost/produto/bebida</con:originalUri><con:credentials><con:authType>No Authorization</con:authType></con:credentials><con:jmsConfig JMSDeliveryMode="PERSISTENT"/><con:jmsPropertyConfig/><con:parameters/></con:request></con:method><con:method name="inclui" id="22458602-ded2-40b6-8d06-be81b335db8c" method="POST"><con:settings/><con:parameters/><con:representation type="REQUEST"><con:mediaType>application/json</con:mediaType><con:params/></con:representation><con:representation type="RESPONSE"><con:mediaType>application/json</con:mediaType><con:status>200</con:status><con:params/><con:element xmlns:beb="http://localhost/produto/bebida">beb:Response</con:element></con:representation><con:request name="Nova Bebida" id="ecf298b3-927c-403e-a45b-2ea6262e3350" mediaType="application/json" postQueryString="false"><con:settings><con:setting id="com.eviware.soapui.impl.wsdl.WsdlRequest@request-headers">&lt;xml-fragment/></con:setting></con:settings><con:encoding>UTF-8</con:encoding><con:endpoint>http://localhost:8080</con:endpoint><con:request>      {
      "nome": "Café com Leite",
      "valor": 5.99,
      "gelada": false,
      "tamanho": 2,
      "marca": "Nestlè"
   }</con:request><con:originalUri>http://localhost/produto/bebida</con:originalUri><con:credentials><con:authType>No Authorization</con:authType></con:credentials><con:jmsConfig JMSDeliveryMode="PERSISTENT"/><con:jmsPropertyConfig/><con:parameters/></con:request></con:method><con:method name="altera" id="8398107c-8514-49b7-99e7-74107d4f2545" method="PUT"><con:settings/><con:parameters/><con:representation type="REQUEST"><con:mediaType>application/json</con:mediaType><con:params/></con:representation><con:representation type="FAULT"><con:mediaType>application/json</con:mediaType><con:status>409</con:status><con:params/><con:element xmlns:beb="http://localhost/produto/bebida">beb:Fault</con:element></con:representation><con:representation type="RESPONSE"><con:mediaType>application/json</con:mediaType><con:status>200</con:status><con:params/><con:element xmlns:beb="http://localhost/produto/bebida">beb:Response</con:element></con:representation><con:request name="Altera Bebida" id="2e0d3273-a96d-4853-9662-bdc2f66062db" mediaType="application/json" postQueryString="false"><con:settings><con:setting id="com.eviware.soapui.impl.wsdl.WsdlRequest@request-headers">&lt;xml-fragment/></con:setting></con:settings><con:encoding>UTF-8</con:encoding><con:endpoint>http://localhost:8080</con:endpoint><con:request>    {
      "nome": "Fanta Uva",
      "valor": 6.99,
      "codigo": 28,
      "gelada": true,
      "tamanho": 2,
      "marca": "Coca-Cola Company"
   }</con:request><con:originalUri>http://localhost/produto/bebida</con:originalUri><con:credentials><con:authType>No Authorization</con:authType></con:credentials><con:jmsConfig JMSDeliveryMode="PERSISTENT"/><con:jmsPropertyConfig/><con:parameters/></con:request></con:method></con:resource><con:resource name="comida" path="comida" id="9e6433b0-aa2a-452e-add5-fffcd9292e78"><con:settings/><con:parameters/><con:method name="inclui" id="7783a7fa-c4ae-4c5f-b2f1-2bcee1e38147" method="POST"><con:settings/><con:parameters/><con:representation type="REQUEST"><con:mediaType>application/json</con:mediaType><con:params/></con:representation><con:representation type="FAULT"><con:mediaType>application/problem+json</con:mediaType><con:status>400</con:status><con:params/><con:element xmlns:com="http://localhost/produto/comida">com:Fault</con:element></con:representation><con:representation type="RESPONSE"><con:mediaType>application/json</con:mediaType><con:status>200</con:status><con:params/><con:element xmlns:com="http://localhost/produto/comida">com:Response</con:element></con:representation><con:request name="Nova comida" id="e5764584-6373-4f25-84cc-e97a22aa6503" mediaType="application/json" postQueryString="false"><con:settings><con:setting id="com.eviware.soapui.impl.wsdl.WsdlRequest@request-headers">&lt;xml-fragment/></con:setting></con:settings><con:encoding>UTF-8</con:encoding><con:endpoint>http://localhost:8080</con:endpoint><con:request>      {
      "nome": "Lasanha de carne",
      "valor": 20.99,
      "peso": 1,
      "vegano": false,
      "ingredientes": "Massa de lasanha, Carne, Molho branco, Molho de tomate"
   }</con:request><con:originalUri>http://localhost/produto/comida</con:originalUri><con:credentials><con:authType>No Authorization</con:authType></con:credentials><con:jmsConfig JMSDeliveryMode="PERSISTENT"/><con:jmsPropertyConfig/><con:parameters/></con:request></con:method><con:method name="lista" id="0628e284-468f-4f9f-89db-57dffda1adfc" method="GET"><con:settings/><con:parameters/><con:representation type="RESPONSE"><con:mediaType>application/json</con:mediaType><con:status>200</con:status><con:params/><con:element>Response</con:element></con:representation><con:request name="Todas as Comidas" id="ca878245-43b6-445a-8c36-6b5264eb3c2f" mediaType="application/json"><con:settings><con:setting id="com.eviware.soapui.impl.wsdl.WsdlRequest@request-headers">&lt;xml-fragment/></con:setting></con:settings><con:encoding>UTF-8</con:encoding><con:endpoint>http://localhost:8080</con:endpoint><con:request/><con:originalUri>http://localhost/produto/comida</con:originalUri><con:credentials><con:authType>No Authorization</con:authType></con:credentials><con:jmsConfig JMSDeliveryMode="PERSISTENT"/><con:jmsPropertyConfig/><con:parameters/></con:request></con:method><con:method name="altera" id="ec9692c8-4764-4a2b-8a28-c741b9ad7102" method="PUT"><con:settings/><con:parameters/><con:representation type="REQUEST"><con:mediaType>application/json</con:mediaType><con:params/></con:representation><con:representation type="RESPONSE"><con:mediaType xsi:nil="true"/><con:status>0</con:status><con:params/><con:element>data</con:element></con:representation><con:representation type="FAULT"><con:mediaType>application/problem+json</con:mediaType><con:status>400</con:status><con:params/><con:element xmlns:com="http://localhost/produto/comida">com:Fault</con:element></con:representation><con:representation type="RESPONSE"><con:mediaType>application/json</con:mediaType><con:status>200</con:status><con:params/><con:element xmlns:com="http://localhost/produto/comida">com:Response</con:element></con:representation><con:request name="Altera Comida" id="71ca2147-acde-4fc9-998b-abe832f1acf1" mediaType="application/json" postQueryString="false"><con:settings><con:setting id="com.eviware.soapui.impl.wsdl.WsdlRequest@request-headers">&lt;xml-fragment/></con:setting></con:settings><con:encoding>UTF-8</con:encoding><con:endpoint>http://localhost:8080</con:endpoint><con:request>   {
      "nome": "Coxinha de frango",
      "valor": 9.99,
      "codigo": 42,
      "peso": 0.5,
      "vegano": false,
      "ingredientes": "Frango, Massa de coxinha, Farinha de rosca, Ovo"
   }</con:request><con:originalUri>http://localhost/produto/comida</con:originalUri><con:credentials><con:authType>No Authorization</con:authType></con:credentials><con:jmsConfig JMSDeliveryMode="PERSISTENT"/><con:jmsPropertyConfig/><con:parameters/></con:request></con:method></con:resource><con:method name="lista" id="d312bdae-a8ef-4a53-80e6-bb79d8fd53a0" method="GET"><con:settings/><con:parameters/><con:representation type="RESPONSE"><con:mediaType>application/json</con:mediaType><con:status>200</con:status><con:params/><con:element>Response</con:element></con:representation><con:representation type="RESPONSE"><con:mediaType xsi:nil="true"/><con:status>0</con:status><con:params/><con:element>data</con:element></con:representation><con:representation type="RESPONSE"><con:mediaType xsi:nil="true"/><con:status>0</con:status><con:params/><con:element>data</con:element></con:representation><con:representation type="RESPONSE"><con:mediaType xsi:nil="true"/><con:status>0</con:status><con:params/><con:element>data</con:element></con:representation><con:representation type="FAULT"><con:mediaType>application/json</con:mediaType><con:status>404</con:status><con:params/><con:element xmlns:prod="http://localhost/produto">prod:Fault</con:element></con:representation><con:request name="Todos Produtos" id="bc1964c5-69e6-476a-adfc-5639c68e9a98" mediaType="application/json"><con:settings><con:setting id="com.eviware.soapui.impl.wsdl.WsdlRequest@request-headers">&lt;xml-fragment/></con:setting></con:settings><con:encoding>UTF-8</con:encoding><con:endpoint>http://localhost:8080</con:endpoint><con:request/><con:originalUri>http://localhost/produto</con:originalUri><con:credentials><con:authType>No Authorization</con:authType></con:credentials><con:jmsConfig JMSDeliveryMode="PERSISTENT"/><con:jmsPropertyConfig/><con:parameters/><con:parameterOrder><con:entry/></con:parameterOrder></con:request></con:method></con:resource><con:resource name="solicitante" path="/solicitante" id="dc596e14-18cd-40ec-a731-137c27eafc7c"><con:settings/><con:parameters/><con:resource name="961.584.180-30" path="961.584.180-30" id="6c163977-65d4-4eb8-aeb4-3341a421c105"><con:settings/><con:parameters/><con:method name="Apaga" id="8506aeda-939b-4691-87a0-b2fc7e43305d" method="DELETE"><con:settings/><con:parameters/><con:representation type="REQUEST"><con:mediaType>application/json</con:mediaType><con:params/></con:representation><con:representation type="RESPONSE"><con:mediaType xsi:nil="true"/><con:status>0</con:status><con:params/><con:element>data</con:element></con:representation><con:representation type="RESPONSE"><con:mediaType>application/json</con:mediaType><con:status>200</con:status><con:params/><con:element xmlns:ns="http://localhost/solicitante/961.584.180-30">ns:Response</con:element></con:representation><con:request name="Apaga Solicitante" id="baab77b8-520b-4a8a-966d-4a091f22709c" mediaType="application/json" postQueryString="false"><con:settings><con:setting id="com.eviware.soapui.impl.wsdl.WsdlRequest@request-headers">&lt;xml-fragment/></con:setting></con:settings><con:endpoint>http://localhost:8080</con:endpoint><con:request/><con:originalUri>http://localhost/solicitante/961.584.180-30</con:originalUri><con:credentials><con:authType>No Authorization</con:authType></con:credentials><con:jmsConfig JMSDeliveryMode="PERSISTENT"/><con:jmsPropertyConfig/><con:parameters/></con:request></con:method></con:resource><con:method name="lista" id="a5c2a430-79a3-4d46-9272-217fefca1b78" method="GET"><con:settings/><con:parameters/><con:representation type="RESPONSE"><con:mediaType>application/json</con:mediaType><con:status>200</con:status><con:params/><con:element>Response</con:element></con:representation><con:representation type="REQUEST"><con:mediaType>application/json</con:mediaType><con:params/></con:representation><con:representation type="FAULT"><con:mediaType>application/json</con:mediaType><con:status>400</con:status><con:params/><con:element xmlns:sol="http://localhost/solicitante">sol:Fault</con:element></con:representation><con:request name="Lista todos os solicitantes" id="0e759805-626c-4908-b906-cec0a52d9d04" mediaType="application/json" postQueryString="false"><con:settings><con:setting id="com.eviware.soapui.impl.wsdl.WsdlRequest@request-headers">&lt;xml-fragment/></con:setting></con:settings><con:encoding>UTF-8</con:encoding><con:endpoint>http://localhost:8080</con:endpoint><con:request>{
  "cpf": "186.033.558-60",
  "nome": "Ana Oliveira da Silva",
  "email": "ana.oliveira@gmail"
}</con:request><con:originalUri>http://localhost/solicitante</con:originalUri><con:credentials><con:authType>No Authorization</con:authType></con:credentials><con:jmsConfig JMSDeliveryMode="PERSISTENT"/><con:jmsPropertyConfig/><con:parameters/></con:request></con:method><con:method name="Adiciona Solicitante" id="33286a08-4e3a-4c00-a52a-e178d13fcf0e" method="POST"><con:settings/><con:parameters/><con:representation type="REQUEST"><con:mediaType>application/json</con:mediaType><con:params/></con:representation><con:representation type="FAULT"><con:mediaType>application/problem+json</con:mediaType><con:status>405</con:status><con:params/><con:element xmlns:sol="http://localhost/solicitante">sol:Fault</con:element></con:representation><con:representation type="RESPONSE"><con:mediaType>application/json</con:mediaType><con:status>200</con:status><con:params/><con:element xmlns:sol="http://localhost/solicitante">sol:Response</con:element></con:representation><con:request name="inclui" id="eee83570-bd28-49b8-b5a3-9bdc668946bc" mediaType="application/json" postQueryString="false"><con:settings><con:setting id="com.eviware.soapui.impl.wsdl.WsdlRequest@request-headers">&lt;xml-fragment/></con:setting></con:settings><con:encoding>UTF-8</con:encoding><con:endpoint>http://localhost:8080</con:endpoint><con:request>{
      "cpf": "313.053.449-01",
      "nome": "Carlos Oliveira",
      "email": "carlos.oliveira@yahoo.com"
   }</con:request><con:originalUri>http://localhost/solicitante</con:originalUri><con:credentials><con:authType>No Authorization</con:authType></con:credentials><con:jmsConfig JMSDeliveryMode="PERSISTENT"/><con:jmsPropertyConfig/><con:parameters/></con:request></con:method><con:method name="altera" id="f139217f-d922-4220-9aba-3b6aea27f579" method="PUT"><con:settings/><con:parameters/><con:representation type="REQUEST"><con:mediaType>application/json</con:mediaType><con:params/></con:representation><con:representation type="FAULT"><con:mediaType>application/problem+json</con:mediaType><con:status>405</con:status><con:params/><con:element xmlns:sol="http://localhost/solicitante">sol:Fault</con:element></con:representation><con:representation type="RESPONSE"><con:mediaType>application/json</con:mediaType><con:status>200</con:status><con:params/><con:element xmlns:sol="http://localhost/solicitante">sol:Response</con:element></con:representation><con:representation type="FAULT"><con:mediaType>application/json</con:mediaType><con:status>400</con:status><con:params/><con:element xmlns:sol="http://localhost/solicitante">sol:Fault</con:element></con:representation><con:request name="Altera Solicitante" id="91be88d0-e827-4c52-b173-5865f9f0da08" mediaType="application/json" postQueryString="false"><con:settings><con:setting id="com.eviware.soapui.impl.wsdl.WsdlRequest@request-headers">&lt;xml-fragment/></con:setting></con:settings><con:encoding>UTF-8</con:encoding><con:endpoint>http://localhost:8080</con:endpoint><con:request>{
       "cpf": "186.033.558-60",
       "nome": "Ana Oliveira da Silva",
       "email": "ana.oliveira@gmail"
}</con:request><con:originalUri>http://localhost/solicitante</con:originalUri><con:credentials><con:authType>No Authorization</con:authType></con:credentials><con:jmsConfig JMSDeliveryMode="PERSISTENT"/><con:jmsPropertyConfig/><con:parameters/></con:request><con:request name="Altera Solicitante Email inválido" id="8f85eedd-2468-442f-96cd-10dfece8dfc3" mediaType="application/json" postQueryString="false"><con:settings/><con:encoding>UTF-8</con:encoding><con:endpoint>http://localhost:8080</con:endpoint><con:request/><con:credentials><con:authType>No Authorization</con:authType></con:credentials><con:jmsConfig JMSDeliveryMode="PERSISTENT"/><con:jmsPropertyConfig/><con:parameters/></con:request></con:method></con:resource><con:resource name="pedido" path="/pedido" id="4484dfda-a9f3-4e04-b26e-c4bb67c06721"><con:settings/><con:parameters/><con:resource name="10" path="10" id="203b8fd7-e0a6-4403-99cc-d711f4c92f59"><con:settings/><con:parameters/><con:method name="consulta" id="218b2900-c96e-4e13-a38e-03dfe268bf58" method="GET"><con:settings/><con:parameters/><con:representation type="RESPONSE"><con:mediaType>application/json</con:mediaType><con:status>200</con:status><con:params/><con:element xmlns:ns="http://localhost/pedido/10">ns:Response</con:element></con:representation><con:request name="Consulta Pedido" id="7bf5c09c-9601-404c-8185-88540ffdc16f" mediaType="application/json"><con:settings><con:setting id="com.eviware.soapui.impl.wsdl.WsdlRequest@request-headers">&lt;xml-fragment/></con:setting></con:settings><con:encoding>UTF-8</con:encoding><con:endpoint>http://localhost:8080</con:endpoint><con:request/><con:originalUri>http://localhost/pedido/10</con:originalUri><con:credentials><con:authType>No Authorization</con:authType></con:credentials><con:jmsConfig JMSDeliveryMode="PERSISTENT"/><con:jmsPropertyConfig/><con:parameters/></con:request></con:method></con:resource><con:resource name="16" path="16" id="1fd240ba-75ac-4bba-8b47-3f2095c040ac"><con:settings/><con:parameters/><con:method name="apaga" id="14c9952a-0342-4fdd-998e-3dc03413ad95" method="DELETE"><con:settings/><con:parameters/><con:representation type="FAULT"><con:mediaType>application/problem+json</con:mediaType><con:status>405</con:status><con:params/><con:element xmlns:ns="http://localhost/pedido/16">ns:Fault</con:element></con:representation><con:representation type="REQUEST"><con:mediaType>application/json</con:mediaType><con:params/></con:representation><con:representation type="RESPONSE"><con:mediaType>application/json</con:mediaType><con:status>200</con:status><con:params/><con:element xmlns:ns="http://localhost/pedido/16">ns:Response</con:element></con:representation><con:representation type="FAULT"><con:mediaType>application/json</con:mediaType><con:status>409</con:status><con:params/><con:element xmlns:ns="http://localhost/pedido/16">ns:Fault</con:element></con:representation><con:request name="apaga pedido" id="43e381eb-5d42-4dc3-bf90-97430404c707" mediaType="application/json" postQueryString="false"><con:settings><con:setting id="com.eviware.soapui.impl.wsdl.WsdlRequest@request-headers">&lt;xml-fragment/></con:setting></con:settings><con:encoding>UTF-8</con:encoding><con:endpoint>http://localhost:8080</con:endpoint><con:request/><con:originalUri>http://localhost/pedido/16</con:originalUri><con:credentials><con:authType>No Authorization</con:authType></con:credentials><con:jmsConfig JMSDeliveryMode="PERSISTENT"/><con:jmsPropertyConfig/><con:parameters/></con:request></con:method></con:resource><con:method name="Lista" id="1670a337-dab5-4684-84c4-5d1d298f80e9" method="GET"><con:settings/><con:parameters/><con:representation type="RESPONSE"><con:mediaType>application/json</con:mediaType><con:status>200</con:status><con:params/><con:element>Response</con:element></con:representation><con:request name="Lista todos os pedidos" id="aa17140e-1f69-4b7f-93a9-b1d51b60256c" mediaType="application/json"><con:settings><con:setting id="com.eviware.soapui.impl.wsdl.WsdlRequest@request-headers">&lt;xml-fragment/></con:setting></con:settings><con:encoding>UTF-8</con:encoding><con:endpoint>http://localhost:8080</con:endpoint><con:request/><con:originalUri>http://localhost/pedido</con:originalUri><con:credentials><con:authType>No Authorization</con:authType></con:credentials><con:jmsConfig JMSDeliveryMode="PERSISTENT"/><con:jmsPropertyConfig/><con:parameters/></con:request></con:method><con:method name="Inclui" id="c571acf0-6120-491f-98b9-cff36af00923" method="POST"><con:settings/><con:parameters/><con:representation type="FAULT"><con:mediaType>application/problem+json</con:mediaType><con:status>405</con:status><con:params/><con:element xmlns:ped="http://localhost/pedido">ped:Fault</con:element></con:representation><con:representation type="REQUEST"><con:mediaType>application/json</con:mediaType><con:params/></con:representation><con:representation type="RESPONSE"><con:mediaType>application/json</con:mediaType><con:status>200</con:status><con:params/><con:element xmlns:ped="http://localhost/pedido">ped:Response</con:element></con:representation><con:representation type="FAULT"><con:mediaType>application/json</con:mediaType><con:status>409</con:status><con:params/><con:element xmlns:ped="http://localhost/pedido">ped:Fault</con:element></con:representation><con:request name="Adiciona Pedido" id="26a80358-7020-4ef8-a202-75d12c9f896e" mediaType="application/json" postQueryString="false"><con:settings><con:setting id="com.eviware.soapui.impl.wsdl.WsdlRequest@request-headers">&lt;xml-fragment/></con:setting></con:settings><con:endpoint>http://localhost:8080</con:endpoint><con:request>            {  
                  "descricao": "Pedido adicionado",
                  "data": "2023-11-05T10:30:00",
                  "web": true,
                  "produtos": [3, 6, 10, 33, 40],
                  "cpfSolicitante":"666.395.597-73"
           }</con:request><con:originalUri>http://localhost/pedido</con:originalUri><con:credentials><con:authType>No Authorization</con:authType></con:credentials><con:jmsConfig JMSDeliveryMode="PERSISTENT"/><con:jmsPropertyConfig/><con:parameters/></con:request><con:request name="Adiciona Pedido com produto não existe" id="4ec89ff0-eac2-4dac-b4d2-72d73228439e" mediaType="application/json" postQueryString="false"><con:settings><con:setting id="com.eviware.soapui.impl.wsdl.WsdlRequest@request-headers">&lt;xml-fragment/></con:setting></con:settings><con:encoding>UTF-8</con:encoding><con:endpoint>http://localhost:8080</con:endpoint><con:request>            {  
                  "descricao": "Pedido adicionado",
                  "data": "2023-11-05T10:30:00",
                  "web": true,
                  "produtos": [3, 6, 10, 33, 100],
                  "cpfSolicitante":"666.395.597-73"
           }</con:request><con:originalUri>http://localhost/pedido</con:originalUri><con:credentials><con:authType>No Authorization</con:authType></con:credentials><con:jmsConfig JMSDeliveryMode="PERSISTENT"/><con:jmsPropertyConfig/><con:parameters/></con:request></con:method><con:method name="Altera" id="09a69c82-1e0f-4c9f-8178-32ede810755a" method="PUT"><con:settings/><con:parameters/><con:representation type="RESPONSE"><con:mediaType>application/json</con:mediaType><con:status>200</con:status><con:params/><con:element xmlns:ped="http://localhost/pedido">ped:Response</con:element></con:representation><con:representation type="REQUEST"><con:mediaType>application/json</con:mediaType><con:params/></con:representation><con:request name="Altera Pedido" id="c5baf93c-a657-4515-8249-edf15a7d6f91" mediaType="application/json" postQueryString="false"><con:settings><con:setting id="com.eviware.soapui.impl.wsdl.WsdlRequest@request-headers">&lt;xml-fragment/></con:setting></con:settings><con:encoding>UTF-8</con:encoding><con:endpoint>http://localhost:8080</con:endpoint><con:request>            {  
            	    "codigo": 1,
                  "descricao": "Pedido alterado",
                  "data": "2023-11-05T10:30:00",
                  "web": true,
                  "produtos": [3, 6, 10, 33, 40],
                  "cpfSolicitante":"666.395.597-73"
           }</con:request><con:originalUri>http://localhost/pedido</con:originalUri><con:credentials><con:authType>No Authorization</con:authType></con:credentials><con:jmsConfig JMSDeliveryMode="PERSISTENT"/><con:jmsPropertyConfig/><con:parameters/></con:request></con:method></con:resource><con:resource name="relatorio" path="/relatorio/vendas" id="af7e82bf-8d51-49de-beee-4a5a4698d49e"><con:settings/><con:parameters/><con:resource name="10" path="2023/10" id="1d33b817-88ec-4dfd-8706-6d09af88f8f0"><con:settings/><con:parameters/><con:resource name="salva" path="salva" id="6e096ce0-7113-4ade-aa05-cebd9f0b0b98"><con:settings/><con:parameters/><con:method name="Salva Relatório" id="15124306-1316-4b36-bea2-c751d72c497a" method="GET"><con:settings/><con:parameters/><con:representation type="FAULT"><con:mediaType>application/json</con:mediaType><con:status>404 500</con:status><con:params/><con:element xmlns:sal="http://localhost/relatorio/2023/10/salva">sal:Fault</con:element></con:representation><con:representation type="RESPONSE"><con:mediaType>application/json</con:mediaType><con:status>200</con:status><con:params/><con:element xmlns:sal="http://localhost/relatorio/2023/10/salva">sal:Response</con:element></con:representation><con:request name="Salva RelatorioVendas-2003-10.md" id="bb86f581-0121-44fe-9fde-ec3f4239a909" mediaType="application/json"><con:settings><con:setting id="com.eviware.soapui.impl.wsdl.WsdlRequest@request-headers">&lt;xml-fragment/></con:setting></con:settings><con:encoding>UTF-8</con:encoding><con:endpoint>http://localhost:8080</con:endpoint><con:request/><con:originalUri>http://localhost/relatorio/2023/10/salva</con:originalUri><con:credentials><con:authType>No Authorization</con:authType></con:credentials><con:jmsConfig JMSDeliveryMode="PERSISTENT"/><con:jmsPropertyConfig/><con:parameters/></con:request></con:method></con:resource><con:method name="Gera Relatório Json" id="bda77e49-fbff-4284-8d23-64b29a48405b" method="GET"><con:settings/><con:parameters/><con:representation type="FAULT"><con:mediaType>application/json</con:mediaType><con:status>400</con:status><con:params/><con:element xmlns:ns="http://localhost/relatorio/2023/10">ns:Fault</con:element></con:representation><con:representation type="RESPONSE"><con:mediaType>application/json</con:mediaType><con:status>200</con:status><con:params/><con:element xmlns:ns="http://localhost/relatorio/2023/10">ns:Response</con:element></con:representation><con:representation type="RESPONSE"><con:mediaType xsi:nil="true"/><con:status>0</con:status><con:params/><con:element>data</con:element></con:representation><con:request name="Gera Relatório" id="812351d2-fda3-42ba-ae08-38db10fe0bd0" mediaType="application/json"><con:settings><con:setting id="com.eviware.soapui.impl.wsdl.WsdlRequest@request-headers">&lt;xml-fragment/></con:setting></con:settings><con:encoding>UTF-8</con:encoding><con:endpoint>http://localhost:8080</con:endpoint><con:request/><con:originalUri>http://localhost/relatorio/2023/10</con:originalUri><con:credentials><con:authType>No Authorization</con:authType></con:credentials><con:jmsConfig JMSDeliveryMode="PERSISTENT"/><con:jmsPropertyConfig/><con:parameters/></con:request></con:method></con:resource><con:resource name="05" path="2023/05" id="22f6c739-0c97-4ac9-ba9e-be99311686a8"><con:settings/><con:parameters/><con:resource name="salva" path="salva" id="804c57d7-eb90-400e-9c14-dee1fb95a887"><con:settings/><con:parameters/><con:method name="Salva" id="adf619f9-87c9-4e80-999d-419c59bd3c9a" method="GET"><con:settings/><con:parameters/><con:representation type="RESPONSE"><con:mediaType>application/json</con:mediaType><con:status>200</con:status><con:params/><con:element xmlns:sal="http://localhost/relatorio/vendas/2023/05/salva">sal:Response</con:element></con:representation><con:request name="Sem Dados" id="1aeb37f6-9529-4c87-b3a8-4cb6df1d4d51" mediaType="application/json"><con:settings><con:setting id="com.eviware.soapui.impl.wsdl.WsdlRequest@request-headers">&lt;xml-fragment/></con:setting></con:settings><con:endpoint>http://localhost:8080</con:endpoint><con:request/><con:originalUri>http://localhost/relatorio/vendas/2023/05/salva</con:originalUri><con:credentials><con:authType>No Authorization</con:authType></con:credentials><con:jmsConfig JMSDeliveryMode="PERSISTENT"/><con:jmsPropertyConfig/><con:parameters/></con:request></con:method></con:resource><con:method name="Gera Relatorio" id="e7d2569f-d239-48c5-998b-1bc9cd37e2cf" method="GET"><con:settings/><con:parameters/><con:representation type="RESPONSE"><con:mediaType xsi:nil="true"/><con:status>0</con:status><con:params/><con:element>data</con:element></con:representation><con:representation type="RESPONSE"><con:mediaType>application/json</con:mediaType><con:status>200</con:status><con:params/><con:element xmlns:ns="http://localhost/relatorio/vendas/2023/05">ns:Response</con:element></con:representation><con:request name="Sem Dados" id="f03665c6-d1ee-449e-9692-96952798096d" mediaType="application/json"><con:settings><con:setting id="com.eviware.soapui.impl.wsdl.WsdlRequest@request-headers">&lt;xml-fragment/></con:setting></con:settings><con:encoding>UTF-8</con:encoding><con:endpoint>http://localhost:8080</con:endpoint><con:request/><con:originalUri>http://localhost/relatorio/vendas/2023/05</con:originalUri><con:credentials><con:authType>No Authorization</con:authType></con:credentials><con:jmsConfig JMSDeliveryMode="PERSISTENT"/><con:jmsPropertyConfig/><con:parameters/></con:request></con:method></con:resource></con:resource></con:interface><con:properties/><con:wssContainer/><con:oAuth2ProfileContainer/><con:oAuth1ProfileContainer/></con:soapui-project>